macro_recorder/__init__.py
macro_recorder/thread.py
MacroRecorder-1.0.3.dist-info/METADATA
MacroRecorder-1.0.3.dist-info/WHEEL
MacroRecorder-1.0.3.dist-info/top_level.txt
MacroRecorder-1.0.3.dist-info/RECORD
