Metadata-Version: 2.1
Name: MacroRecorder
Version: 1.0.3
Summary: The best and most accurate macro recorder for Windows. Easy to use and open source.
Home-page: UNKNOWN
Author: Eshqol Development
Author-email: support@eshqol.com
License: MIT
Platform: UNKNOWN
Requires-Python: >=3.6
Requires-Dist: keyboard
Requires-Dist: mouse
